tcd_pipeline/__init__.py
tcd_pipeline/__main__.py
tcd_pipeline/commands/generate_workflows.py
tcd_pipeline/config/logging.yaml
tcd_pipeline/config/logging_config.py
tcd_pipeline/pipeline.py
tcd_pipeline/rules/changes.py
tcd_pipeline/rules/push.py
tcd_pipeline/templates/local_template.py
tcd_pipeline-0.2.6.dist-info/entry_points.txt
tcd_pipeline-0.2.6.dist-info/WHEEL
tcd_pipeline-0.2.6.dist-info/METADATA
tcd_pipeline-0.2.6.dist-info/RECORD
