Metadata-Version: 2.1
Name: tcd-pipeline
Version: 0.2.6
Summary: 
Author: chitchai
Author-email: chitchaic@gmail.com
Requires-Python: >=3.10,<4.0
Classifier: Programming Language :: Python :: 3
Classifier: Programming Language :: Python :: 3.10
Classifier: Programming Language :: Python :: 3.11
Requires-Dist: PyYAML (>=6.0,<7.0)
Requires-Dist: click (>=8.1.3,<9.0.0)
Requires-Dist: jsonpath-ng (>=1.5.3,<2.0.0)
